{"cameraMode":{"drawMode":0,"name":"Shaded","section":"Shading Mode"},"sceneLighting":false,"audioPlay":false,"sceneViewState":{"m_AlwaysRefresh":false,"showFog":true,"showSkybox":false,"showFlares":true,"showImageEffects":true,"showParticleSystems":true,"showVisualEffectGraphs":true,"m_FxEnabled":true},"in2DMode":false,"pivot":{"x":0.6453144550323486,"y":0.5137190222740173,"z":4.069328308105469},"rotation":{"x":0.1291828453540802,"y":-0.5394107103347778,"z":0.08417120575904846,"w":0.8278252482414246},"size":2.3186893463134767,"orthographic":false}